[
  {
    "id": 1,
    "subname": "bangla",
    "teacher": "md ismaile hossain",
    "ratting": "4 star"
  },
  {
    "id": 2,
    "subname": "english",
    "teacher": "md jisan ahmed",
    "ratting": "4 star"
  },
  {
    "id": 3,
    "subname": "math",
    "teacher": "md shihab hossain",
    "ratting": "5 star"
  },
  {
    "id": 4,
    "subname": "ict",
    "teacher": "md noman hossain",
    "ratting": "3 star"
  },
  {
    "id": 5,
    "subname": "chemistry",
    "teacher": "md hassan",
    "ratting": "5 star"
  },
  {
    "id": 6,
    "subname": "biology",
    "teacher": "omar faruk",
    "ratting": "5 star"
  },
  {
    "id": 7,
    "subname": "physics",
    "teacher": "md jubayer hossain",
    "ratting": "5 star"
  },
  {
    "id": 8,
    "subname": "finance",
    "teacher": "hossain khan",
    "ratting": "2 star"
  },
  {
    "id": 9,
    "subname": "general scince",
    "teacher": "md monir hossain",
    "ratting": "4 star"
  },
  {
    "id": 10,
    "subname": "higher math",
    "teacher": "arafat hossain",
    "ratting": "5 star"
  },
  {
    "id": 11,
    "subname": "quran",
    "teacher": "md mizanur rahman",
    "ratting": "4 star"
  },
  {
    "id": 12,
    "subname": "hadith",
    "teacher": "md abdullah",
    "ratting": "3 star"
  }
]